{"nodes": [{"id": "d_projects_ev_charging_mvp_backend_vendor_laravel_framework_src_illuminate_cookie_cookieserviceprovider_php", "label": "CookieServiceProvider.php", "file_type": "code", "source_file": "D:\\Projects\\ev-charging-mvp\\backend\\vendor\\laravel\\framework\\src\\Illuminate\\Cookie\\CookieServiceProvider.php", "source_location": "L1"}, {"id": "cookie_cookieserviceprovider_cookieserviceprovider", "label": "CookieServiceProvider", "file_type": "code", "source_file": "D:\\Projects\\ev-charging-mvp\\backend\\vendor\\laravel\\framework\\src\\Illuminate\\Cookie\\CookieServiceProvider.php", "source_location": "L7"}, {"id": "cookie_cookieserviceprovider_cookieserviceprovider_register", "label": ".register()", "file_type": "code", "source_file": "D:\\Projects\\ev-charging-mvp\\backend\\vendor\\laravel\\framework\\src\\Illuminate\\Cookie\\CookieServiceProvider.php", "source_location": "L14"}], "edges": [{"source": "d_projects_ev_charging_mvp_backend_vendor_laravel_framework_src_illuminate_cookie_cookieserviceprovider_php", "target": "serviceprovider", "relation": "imports", "confidence": "EXTRACTED", "source_file": "D:\\Projects\\ev-charging-mvp\\backend\\vendor\\laravel\\framework\\src\\Illuminate\\Cookie\\CookieServiceProvider.php", "source_location": "L5", "weight": 1.0}, {"source": "d_projects_ev_charging_mvp_backend_vendor_laravel_framework_src_illuminate_cookie_cookieserviceprovider_php", "target": "cookie_cookieserviceprovider_cookieserviceprovider", "relation": "contains", "confidence": "EXTRACTED", "source_file": "D:\\Projects\\ev-charging-mvp\\backend\\vendor\\laravel\\framework\\src\\Illuminate\\Cookie\\CookieServiceProvider.php", "source_location": "L7", "weight": 1.0}, {"source": "cookie_cookieserviceprovider_cookieserviceprovider", "target": "cookie_cookieserviceprovider_cookieserviceprovider_register", "relation": "method", "confidence": "EXTRACTED", "source_file": "D:\\Projects\\ev-charging-mvp\\backend\\vendor\\laravel\\framework\\src\\Illuminate\\Cookie\\CookieServiceProvider.php", "source_location": "L14", "weight": 1.0}], "raw_calls": [{"caller_nid": "cookie_cookieserviceprovider_cookieserviceprovider_register", "callee": "singleton", "source_file": "D:\\Projects\\ev-charging-mvp\\backend\\vendor\\laravel\\framework\\src\\Illuminate\\Cookie\\CookieServiceProvider.php", "source_location": "L16"}, {"caller_nid": "cookie_cookieserviceprovider_cookieserviceprovider_register", "callee": "get", "source_file": "D:\\Projects\\ev-charging-mvp\\backend\\vendor\\laravel\\framework\\src\\Illuminate\\Cookie\\CookieServiceProvider.php", "source_location": "L17"}, {"caller_nid": "cookie_cookieserviceprovider_cookieserviceprovider_register", "callee": "make", "source_file": "D:\\Projects\\ev-charging-mvp\\backend\\vendor\\laravel\\framework\\src\\Illuminate\\Cookie\\CookieServiceProvider.php", "source_location": "L17"}, {"caller_nid": "cookie_cookieserviceprovider_cookieserviceprovider_register", "callee": "setDefaultPathAndDomain", "source_file": "D:\\Projects\\ev-charging-mvp\\backend\\vendor\\laravel\\framework\\src\\Illuminate\\Cookie\\CookieServiceProvider.php", "source_location": "L19"}]}