{"nodes": [{"id": "d_projects_ev_charging_mvp_react_bits_src_src_content_components_stepper_stepper_jsx", "label": "Stepper.jsx", "file_type": "code", "source_file": "D:\\Projects\\ev-charging-mvp\\react-bits-src\\src\\content\\Components\\Stepper\\Stepper.jsx", "source_location": "L1"}, {"id": "stepper_stepper_stepper", "label": "Stepper()", "file_type": "code", "source_file": "D:\\Projects\\ev-charging-mvp\\react-bits-src\\src\\content\\Components\\Stepper\\Stepper.jsx", "source_location": "L6"}, {"id": "stepper_stepper_stepcontentwrapper", "label": "StepContentWrapper()", "file_type": "code", "source_file": "D:\\Projects\\ev-charging-mvp\\react-bits-src\\src\\content\\Components\\Stepper\\Stepper.jsx", "source_location": "L125"}, {"id": "stepper_stepper_slidetransition", "label": "SlideTransition()", "file_type": "code", "source_file": "D:\\Projects\\ev-charging-mvp\\react-bits-src\\src\\content\\Components\\Stepper\\Stepper.jsx", "source_location": "L146"}, {"id": "stepper_stepper_step", "label": "Step()", "file_type": "code", "source_file": "D:\\Projects\\ev-charging-mvp\\react-bits-src\\src\\content\\Components\\Stepper\\Stepper.jsx", "source_location": "L184"}, {"id": "stepper_stepper_stepindicator", "label": "StepIndicator()", "file_type": "code", "source_file": "D:\\Projects\\ev-charging-mvp\\react-bits-src\\src\\content\\Components\\Stepper\\Stepper.jsx", "source_location": "L188"}, {"id": "stepper_stepper_stepconnector", "label": "StepConnector()", "file_type": "code", "source_file": "D:\\Projects\\ev-charging-mvp\\react-bits-src\\src\\content\\Components\\Stepper\\Stepper.jsx", "source_location": "L218"}, {"id": "stepper_stepper_checkicon", "label": "CheckIcon()", "file_type": "code", "source_file": "D:\\Projects\\ev-charging-mvp\\react-bits-src\\src\\content\\Components\\Stepper\\Stepper.jsx", "source_location": "L237"}], "edges": [{"source": "d_projects_ev_charging_mvp_react_bits_src_src_content_components_stepper_stepper_jsx", "target": "react", "relation": "imports_from", "confidence": "EXTRACTED", "source_file": "D:\\Projects\\ev-charging-mvp\\react-bits-src\\src\\content\\Components\\Stepper\\Stepper.jsx", "source_location": "L1", "weight": 1.0}, {"source": "d_projects_ev_charging_mvp_react_bits_src_src_content_components_stepper_stepper_jsx", "target": "react", "relation": "imports_from", "confidence": "EXTRACTED", "source_file": "D:\\Projects\\ev-charging-mvp\\react-bits-src\\src\\content\\Components\\Stepper\\Stepper.jsx", "source_location": "L2", "weight": 1.0}, {"source": "d_projects_ev_charging_mvp_react_bits_src_src_content_components_stepper_stepper_jsx", "target": "d_projects_ev_charging_mvp_react_bits_src_src_content_components_stepper_stepper_css", "relation": "imports_from", "confidence": "EXTRACTED", "source_file": "D:\\Projects\\ev-charging-mvp\\react-bits-src\\src\\content\\Components\\Stepper\\Stepper.jsx", "source_location": "L4", "weight": 1.0}, {"source": "d_projects_ev_charging_mvp_react_bits_src_src_content_components_stepper_stepper_jsx", "target": "stepper_stepper_stepper", "relation": "contains", "confidence": "EXTRACTED", "source_file": "D:\\Projects\\ev-charging-mvp\\react-bits-src\\src\\content\\Components\\Stepper\\Stepper.jsx", "source_location": "L6", "weight": 1.0}, {"source": "d_projects_ev_charging_mvp_react_bits_src_src_content_components_stepper_stepper_jsx", "target": "stepper_stepper_stepcontentwrapper", "relation": "contains", "confidence": "EXTRACTED", "source_file": "D:\\Projects\\ev-charging-mvp\\react-bits-src\\src\\content\\Components\\Stepper\\Stepper.jsx", "source_location": "L125", "weight": 1.0}, {"source": "d_projects_ev_charging_mvp_react_bits_src_src_content_components_stepper_stepper_jsx", "target": "stepper_stepper_slidetransition", "relation": "contains", "confidence": "EXTRACTED", "source_file": "D:\\Projects\\ev-charging-mvp\\react-bits-src\\src\\content\\Components\\Stepper\\Stepper.jsx", "source_location": "L146", "weight": 1.0}, {"source": "d_projects_ev_charging_mvp_react_bits_src_src_content_components_stepper_stepper_jsx", "target": "stepper_stepper_step", "relation": "contains", "confidence": "EXTRACTED", "source_file": "D:\\Projects\\ev-charging-mvp\\react-bits-src\\src\\content\\Components\\Stepper\\Stepper.jsx", "source_location": "L184", "weight": 1.0}, {"source": "d_projects_ev_charging_mvp_react_bits_src_src_content_components_stepper_stepper_jsx", "target": "stepper_stepper_stepindicator", "relation": "contains", "confidence": "EXTRACTED", "source_file": "D:\\Projects\\ev-charging-mvp\\react-bits-src\\src\\content\\Components\\Stepper\\Stepper.jsx", "source_location": "L188", "weight": 1.0}, {"source": "d_projects_ev_charging_mvp_react_bits_src_src_content_components_stepper_stepper_jsx", "target": "stepper_stepper_stepconnector", "relation": "contains", "confidence": "EXTRACTED", "source_file": "D:\\Projects\\ev-charging-mvp\\react-bits-src\\src\\content\\Components\\Stepper\\Stepper.jsx", "source_location": "L218", "weight": 1.0}, {"source": "d_projects_ev_charging_mvp_react_bits_src_src_content_components_stepper_stepper_jsx", "target": "stepper_stepper_checkicon", "relation": "contains", "confidence": "EXTRACTED", "source_file": "D:\\Projects\\ev-charging-mvp\\react-bits-src\\src\\content\\Components\\Stepper\\Stepper.jsx", "source_location": "L237", "weight": 1.0}], "raw_calls": [{"caller_nid": "stepper_stepper_stepper", "callee": "useState", "source_file": "D:\\Projects\\ev-charging-mvp\\react-bits-src\\src\\content\\Components\\Stepper\\Stepper.jsx", "source_location": "L23"}, {"caller_nid": "stepper_stepper_stepper", "callee": "useState", "source_file": "D:\\Projects\\ev-charging-mvp\\react-bits-src\\src\\content\\Components\\Stepper\\Stepper.jsx", "source_location": "L24"}, {"caller_nid": "stepper_stepper_stepper", "callee": "toArray", "source_file": "D:\\Projects\\ev-charging-mvp\\react-bits-src\\src\\content\\Components\\Stepper\\Stepper.jsx", "source_location": "L25"}, {"caller_nid": "stepper_stepper_stepper", "callee": "map", "source_file": "D:\\Projects\\ev-charging-mvp\\react-bits-src\\src\\content\\Components\\Stepper\\Stepper.jsx", "source_location": "L62"}, {"caller_nid": "stepper_stepper_stepcontentwrapper", "callee": "useState", "source_file": "D:\\Projects\\ev-charging-mvp\\react-bits-src\\src\\content\\Components\\Stepper\\Stepper.jsx", "source_location": "L126"}, {"caller_nid": "stepper_stepper_slidetransition", "callee": "useRef", "source_file": "D:\\Projects\\ev-charging-mvp\\react-bits-src\\src\\content\\Components\\Stepper\\Stepper.jsx", "source_location": "L147"}, {"caller_nid": "stepper_stepper_slidetransition", "callee": "useLayoutEffect", "source_file": "D:\\Projects\\ev-charging-mvp\\react-bits-src\\src\\content\\Components\\Stepper\\Stepper.jsx", "source_location": "L149"}]}