{"nodes": [{"id": "d_projects_ev_charging_mvp_react_bits_src_src_ts_tailwind_backgrounds_prismaticburst_prismaticburst_tsx", "label": "PrismaticBurst.tsx", "file_type": "code", "source_file": "D:\\Projects\\ev-charging-mvp\\react-bits-src\\src\\ts-tailwind\\Backgrounds\\PrismaticBurst\\PrismaticBurst.tsx", "source_location": "L1"}, {"id": "prismaticburst_prismaticburst_hextorgb01", "label": "hexToRgb01()", "file_type": "code", "source_file": "D:\\Projects\\ev-charging-mvp\\react-bits-src\\src\\ts-tailwind\\Backgrounds\\PrismaticBurst\\PrismaticBurst.tsx", "source_location": "L193"}, {"id": "prismaticburst_prismaticburst_topx", "label": "toPx()", "file_type": "code", "source_file": "D:\\Projects\\ev-charging-mvp\\react-bits-src\\src\\ts-tailwind\\Backgrounds\\PrismaticBurst\\PrismaticBurst.tsx", "source_location": "L210"}, {"id": "prismaticburst_prismaticburst_resize", "label": "resize()", "file_type": "code", "source_file": "D:\\Projects\\ev-charging-mvp\\react-bits-src\\src\\ts-tailwind\\Backgrounds\\PrismaticBurst\\PrismaticBurst.tsx", "source_location": "L307"}, {"id": "prismaticburst_prismaticburst_onpointer", "label": "onPointer()", "file_type": "code", "source_file": "D:\\Projects\\ev-charging-mvp\\react-bits-src\\src\\ts-tailwind\\Backgrounds\\PrismaticBurst\\PrismaticBurst.tsx", "source_location": "L323"}, {"id": "prismaticburst_prismaticburst_onvis", "label": "onVis()", "file_type": "code", "source_file": "D:\\Projects\\ev-charging-mvp\\react-bits-src\\src\\ts-tailwind\\Backgrounds\\PrismaticBurst\\PrismaticBurst.tsx", "source_location": "L341"}, {"id": "prismaticburst_prismaticburst_update", "label": "update()", "file_type": "code", "source_file": "D:\\Projects\\ev-charging-mvp\\react-bits-src\\src\\ts-tailwind\\Backgrounds\\PrismaticBurst\\PrismaticBurst.tsx", "source_location": "L348"}], "edges": [{"source": "d_projects_ev_charging_mvp_react_bits_src_src_ts_tailwind_backgrounds_prismaticburst_prismaticburst_tsx", "target": "react", "relation": "imports_from", "confidence": "EXTRACTED", "source_file": "D:\\Projects\\ev-charging-mvp\\react-bits-src\\src\\ts-tailwind\\Backgrounds\\PrismaticBurst\\PrismaticBurst.tsx", "source_location": "L1", "weight": 1.0}, {"source": "d_projects_ev_charging_mvp_react_bits_src_src_ts_tailwind_backgrounds_prismaticburst_prismaticburst_tsx", "target": "ogl", "relation": "imports_from", "confidence": "EXTRACTED", "source_file": "D:\\Projects\\ev-charging-mvp\\react-bits-src\\src\\ts-tailwind\\Backgrounds\\PrismaticBurst\\PrismaticBurst.tsx", "source_location": "L2", "weight": 1.0}, {"source": "d_projects_ev_charging_mvp_react_bits_src_src_ts_tailwind_backgrounds_prismaticburst_prismaticburst_tsx", "target": "prismaticburst_prismaticburst_hextorgb01", "relation": "contains", "confidence": "EXTRACTED", "source_file": "D:\\Projects\\ev-charging-mvp\\react-bits-src\\src\\ts-tailwind\\Backgrounds\\PrismaticBurst\\PrismaticBurst.tsx", "source_location": "L193", "weight": 1.0}, {"source": "d_projects_ev_charging_mvp_react_bits_src_src_ts_tailwind_backgrounds_prismaticburst_prismaticburst_tsx", "target": "prismaticburst_prismaticburst_topx", "relation": "contains", "confidence": "EXTRACTED", "source_file": "D:\\Projects\\ev-charging-mvp\\react-bits-src\\src\\ts-tailwind\\Backgrounds\\PrismaticBurst\\PrismaticBurst.tsx", "source_location": "L210", "weight": 1.0}, {"source": "d_projects_ev_charging_mvp_react_bits_src_src_ts_tailwind_backgrounds_prismaticburst_prismaticburst_tsx", "target": "prismaticburst_prismaticburst_resize", "relation": "contains", "confidence": "EXTRACTED", "source_file": "D:\\Projects\\ev-charging-mvp\\react-bits-src\\src\\ts-tailwind\\Backgrounds\\PrismaticBurst\\PrismaticBurst.tsx", "source_location": "L307", "weight": 1.0}, {"source": "d_projects_ev_charging_mvp_react_bits_src_src_ts_tailwind_backgrounds_prismaticburst_prismaticburst_tsx", "target": "prismaticburst_prismaticburst_onpointer", "relation": "contains", "confidence": "EXTRACTED", "source_file": "D:\\Projects\\ev-charging-mvp\\react-bits-src\\src\\ts-tailwind\\Backgrounds\\PrismaticBurst\\PrismaticBurst.tsx", "source_location": "L323", "weight": 1.0}, {"source": "d_projects_ev_charging_mvp_react_bits_src_src_ts_tailwind_backgrounds_prismaticburst_prismaticburst_tsx", "target": "prismaticburst_prismaticburst_onvis", "relation": "contains", "confidence": "EXTRACTED", "source_file": "D:\\Projects\\ev-charging-mvp\\react-bits-src\\src\\ts-tailwind\\Backgrounds\\PrismaticBurst\\PrismaticBurst.tsx", "source_location": "L341", "weight": 1.0}, {"source": "d_projects_ev_charging_mvp_react_bits_src_src_ts_tailwind_backgrounds_prismaticburst_prismaticburst_tsx", "target": "prismaticburst_prismaticburst_update", "relation": "contains", "confidence": "EXTRACTED", "source_file": "D:\\Projects\\ev-charging-mvp\\react-bits-src\\src\\ts-tailwind\\Backgrounds\\PrismaticBurst\\PrismaticBurst.tsx", "source_location": "L348", "weight": 1.0}], "raw_calls": [{"caller_nid": "prismaticburst_prismaticburst_hextorgb01", "callee": "trim", "source_file": "D:\\Projects\\ev-charging-mvp\\react-bits-src\\src\\ts-tailwind\\Backgrounds\\PrismaticBurst\\PrismaticBurst.tsx", "source_location": "L194"}, {"caller_nid": "prismaticburst_prismaticburst_hextorgb01", "callee": "startsWith", "source_file": "D:\\Projects\\ev-charging-mvp\\react-bits-src\\src\\ts-tailwind\\Backgrounds\\PrismaticBurst\\PrismaticBurst.tsx", "source_location": "L195"}, {"caller_nid": "prismaticburst_prismaticburst_hextorgb01", "callee": "slice", "source_file": "D:\\Projects\\ev-charging-mvp\\react-bits-src\\src\\ts-tailwind\\Backgrounds\\PrismaticBurst\\PrismaticBurst.tsx", "source_location": "L195"}, {"caller_nid": "prismaticburst_prismaticburst_hextorgb01", "callee": "parseInt", "source_file": "D:\\Projects\\ev-charging-mvp\\react-bits-src\\src\\ts-tailwind\\Backgrounds\\PrismaticBurst\\PrismaticBurst.tsx", "source_location": "L202"}, {"caller_nid": "prismaticburst_prismaticburst_hextorgb01", "callee": "isNaN", "source_file": "D:\\Projects\\ev-charging-mvp\\react-bits-src\\src\\ts-tailwind\\Backgrounds\\PrismaticBurst\\PrismaticBurst.tsx", "source_location": "L203"}, {"caller_nid": "prismaticburst_prismaticburst_topx", "callee": "trim", "source_file": "D:\\Projects\\ev-charging-mvp\\react-bits-src\\src\\ts-tailwind\\Backgrounds\\PrismaticBurst\\PrismaticBurst.tsx", "source_location": "L213"}, {"caller_nid": "prismaticburst_prismaticburst_topx", "callee": "String", "source_file": "D:\\Projects\\ev-charging-mvp\\react-bits-src\\src\\ts-tailwind\\Backgrounds\\PrismaticBurst\\PrismaticBurst.tsx", "source_location": "L213"}, {"caller_nid": "prismaticburst_prismaticburst_topx", "callee": "parseFloat", "source_file": "D:\\Projects\\ev-charging-mvp\\react-bits-src\\src\\ts-tailwind\\Backgrounds\\PrismaticBurst\\PrismaticBurst.tsx", "source_location": "L214"}, {"caller_nid": "prismaticburst_prismaticburst_topx", "callee": "replace", "source_file": "D:\\Projects\\ev-charging-mvp\\react-bits-src\\src\\ts-tailwind\\Backgrounds\\PrismaticBurst\\PrismaticBurst.tsx", "source_location": "L214"}, {"caller_nid": "prismaticburst_prismaticburst_topx", "callee": "isNaN", "source_file": "D:\\Projects\\ev-charging-mvp\\react-bits-src\\src\\ts-tailwind\\Backgrounds\\PrismaticBurst\\PrismaticBurst.tsx", "source_location": "L215"}, {"caller_nid": "prismaticburst_prismaticburst_resize", "callee": "setSize", "source_file": "D:\\Projects\\ev-charging-mvp\\react-bits-src\\src\\ts-tailwind\\Backgrounds\\PrismaticBurst\\PrismaticBurst.tsx", "source_location": "L310"}, {"caller_nid": "prismaticburst_prismaticburst_onpointer", "callee": "getBoundingClientRect", "source_file": "D:\\Projects\\ev-charging-mvp\\react-bits-src\\src\\ts-tailwind\\Backgrounds\\PrismaticBurst\\PrismaticBurst.tsx", "source_location": "L324"}, {"caller_nid": "prismaticburst_prismaticburst_onpointer", "callee": "max", "source_file": "D:\\Projects\\ev-charging-mvp\\react-bits-src\\src\\ts-tailwind\\Backgrounds\\PrismaticBurst\\PrismaticBurst.tsx", "source_location": "L325"}, {"caller_nid": "prismaticburst_prismaticburst_onpointer", "callee": "max", "source_file": "D:\\Projects\\ev-charging-mvp\\react-bits-src\\src\\ts-tailwind\\Backgrounds\\PrismaticBurst\\PrismaticBurst.tsx", "source_location": "L326"}, {"caller_nid": "prismaticburst_prismaticburst_onpointer", "callee": "min", "source_file": "D:\\Projects\\ev-charging-mvp\\react-bits-src\\src\\ts-tailwind\\Backgrounds\\PrismaticBurst\\PrismaticBurst.tsx", "source_location": "L327"}, {"caller_nid": "prismaticburst_prismaticburst_onpointer", "callee": "max", "source_file": "D:\\Projects\\ev-charging-mvp\\react-bits-src\\src\\ts-tailwind\\Backgrounds\\PrismaticBurst\\PrismaticBurst.tsx", "source_location": "L327"}, {"caller_nid": "prismaticburst_prismaticburst_onpointer", "callee": "min", "source_file": "D:\\Projects\\ev-charging-mvp\\react-bits-src\\src\\ts-tailwind\\Backgrounds\\PrismaticBurst\\PrismaticBurst.tsx", "source_location": "L327"}, {"caller_nid": "prismaticburst_prismaticburst_onpointer", "callee": "max", "source_file": "D:\\Projects\\ev-charging-mvp\\react-bits-src\\src\\ts-tailwind\\Backgrounds\\PrismaticBurst\\PrismaticBurst.tsx", "source_location": "L327"}, {"caller_nid": "prismaticburst_prismaticburst_update", "callee": "max", "source_file": "D:\\Projects\\ev-charging-mvp\\react-bits-src\\src\\ts-tailwind\\Backgrounds\\PrismaticBurst\\PrismaticBurst.tsx", "source_location": "L349"}, {"caller_nid": "prismaticburst_prismaticburst_update", "callee": "requestAnimationFrame", "source_file": "D:\\Projects\\ev-charging-mvp\\react-bits-src\\src\\ts-tailwind\\Backgrounds\\PrismaticBurst\\PrismaticBurst.tsx", "source_location": "L354"}, {"caller_nid": "prismaticburst_prismaticburst_update", "callee": "max", "source_file": "D:\\Projects\\ev-charging-mvp\\react-bits-src\\src\\ts-tailwind\\Backgrounds\\PrismaticBurst\\PrismaticBurst.tsx", "source_location": "L357"}, {"caller_nid": "prismaticburst_prismaticburst_update", "callee": "min", "source_file": "D:\\Projects\\ev-charging-mvp\\react-bits-src\\src\\ts-tailwind\\Backgrounds\\PrismaticBurst\\PrismaticBurst.tsx", "source_location": "L357"}, {"caller_nid": "prismaticburst_prismaticburst_update", "callee": "exp", "source_file": "D:\\Projects\\ev-charging-mvp\\react-bits-src\\src\\ts-tailwind\\Backgrounds\\PrismaticBurst\\PrismaticBurst.tsx", "source_location": "L358"}, {"caller_nid": "prismaticburst_prismaticburst_update", "callee": "render", "source_file": "D:\\Projects\\ev-charging-mvp\\react-bits-src\\src\\ts-tailwind\\Backgrounds\\PrismaticBurst\\PrismaticBurst.tsx", "source_location": "L365"}, {"caller_nid": "prismaticburst_prismaticburst_update", "callee": "requestAnimationFrame", "source_file": "D:\\Projects\\ev-charging-mvp\\react-bits-src\\src\\ts-tailwind\\Backgrounds\\PrismaticBurst\\PrismaticBurst.tsx", "source_location": "L366"}]}