{"nodes": [{"id": "d_projects_ev_charging_mvp_react_bits_src_src_content_textanimations_shinytext_shinytext_jsx", "label": "ShinyText.jsx", "file_type": "code", "source_file": "D:\\Projects\\ev-charging-mvp\\react-bits-src\\src\\content\\TextAnimations\\ShinyText\\ShinyText.jsx", "source_location": "L1"}, {"id": "shinytext_shinytext_shinytext", "label": "ShinyText()", "file_type": "code", "source_file": "D:\\Projects\\ev-charging-mvp\\react-bits-src\\src\\content\\TextAnimations\\ShinyText\\ShinyText.jsx", "source_location": "L5"}], "edges": [{"source": "d_projects_ev_charging_mvp_react_bits_src_src_content_textanimations_shinytext_shinytext_jsx", "target": "react", "relation": "imports_from", "confidence": "EXTRACTED", "source_file": "D:\\Projects\\ev-charging-mvp\\react-bits-src\\src\\content\\TextAnimations\\ShinyText\\ShinyText.jsx", "source_location": "L1", "weight": 1.0}, {"source": "d_projects_ev_charging_mvp_react_bits_src_src_content_textanimations_shinytext_shinytext_jsx", "target": "react", "relation": "imports_from", "confidence": "EXTRACTED", "source_file": "D:\\Projects\\ev-charging-mvp\\react-bits-src\\src\\content\\TextAnimations\\ShinyText\\ShinyText.jsx", "source_location": "L2", "weight": 1.0}, {"source": "d_projects_ev_charging_mvp_react_bits_src_src_content_textanimations_shinytext_shinytext_jsx", "target": "d_projects_ev_charging_mvp_react_bits_src_src_content_textanimations_shinytext_shinytext_css", "relation": "imports_from", "confidence": "EXTRACTED", "source_file": "D:\\Projects\\ev-charging-mvp\\react-bits-src\\src\\content\\TextAnimations\\ShinyText\\ShinyText.jsx", "source_location": "L3", "weight": 1.0}, {"source": "d_projects_ev_charging_mvp_react_bits_src_src_content_textanimations_shinytext_shinytext_jsx", "target": "shinytext_shinytext_shinytext", "relation": "contains", "confidence": "EXTRACTED", "source_file": "D:\\Projects\\ev-charging-mvp\\react-bits-src\\src\\content\\TextAnimations\\ShinyText\\ShinyText.jsx", "source_location": "L5", "weight": 1.0}], "raw_calls": [{"caller_nid": "shinytext_shinytext_shinytext", "callee": "useState", "source_file": "D:\\Projects\\ev-charging-mvp\\react-bits-src\\src\\content\\TextAnimations\\ShinyText\\ShinyText.jsx", "source_location": "L18"}, {"caller_nid": "shinytext_shinytext_shinytext", "callee": "useMotionValue", "source_file": "D:\\Projects\\ev-charging-mvp\\react-bits-src\\src\\content\\TextAnimations\\ShinyText\\ShinyText.jsx", "source_location": "L19"}, {"caller_nid": "shinytext_shinytext_shinytext", "callee": "useRef", "source_file": "D:\\Projects\\ev-charging-mvp\\react-bits-src\\src\\content\\TextAnimations\\ShinyText\\ShinyText.jsx", "source_location": "L20"}, {"caller_nid": "shinytext_shinytext_shinytext", "callee": "useRef", "source_file": "D:\\Projects\\ev-charging-mvp\\react-bits-src\\src\\content\\TextAnimations\\ShinyText\\ShinyText.jsx", "source_location": "L21"}, {"caller_nid": "shinytext_shinytext_shinytext", "callee": "useRef", "source_file": "D:\\Projects\\ev-charging-mvp\\react-bits-src\\src\\content\\TextAnimations\\ShinyText\\ShinyText.jsx", "source_location": "L22"}, {"caller_nid": "shinytext_shinytext_shinytext", "callee": "useAnimationFrame", "source_file": "D:\\Projects\\ev-charging-mvp\\react-bits-src\\src\\content\\TextAnimations\\ShinyText\\ShinyText.jsx", "source_location": "L27"}, {"caller_nid": "shinytext_shinytext_shinytext", "callee": "useEffect", "source_file": "D:\\Projects\\ev-charging-mvp\\react-bits-src\\src\\content\\TextAnimations\\ShinyText\\ShinyText.jsx", "source_location": "L79"}, {"caller_nid": "shinytext_shinytext_shinytext", "callee": "useTransform", "source_file": "D:\\Projects\\ev-charging-mvp\\react-bits-src\\src\\content\\TextAnimations\\ShinyText\\ShinyText.jsx", "source_location": "L87"}, {"caller_nid": "shinytext_shinytext_shinytext", "callee": "useCallback", "source_file": "D:\\Projects\\ev-charging-mvp\\react-bits-src\\src\\content\\TextAnimations\\ShinyText\\ShinyText.jsx", "source_location": "L89"}, {"caller_nid": "shinytext_shinytext_shinytext", "callee": "useCallback", "source_file": "D:\\Projects\\ev-charging-mvp\\react-bits-src\\src\\content\\TextAnimations\\ShinyText\\ShinyText.jsx", "source_location": "L93"}]}