{"nodes": [{"id": "d_projects_ev_charging_mvp_backend_vendor_laravel_prompts_src_concerns_truncation_php", "label": "Truncation.php", "file_type": "code", "source_file": "D:\\Projects\\ev-charging-mvp\\backend\\vendor\\laravel\\prompts\\src\\Concerns\\Truncation.php", "source_location": "L1"}, {"id": "concerns_truncation_truncate", "label": "truncate()", "file_type": "code", "source_file": "D:\\Projects\\ev-charging-mvp\\backend\\vendor\\laravel\\prompts\\src\\Concerns\\Truncation.php", "source_location": "L12"}], "edges": [{"source": "d_projects_ev_charging_mvp_backend_vendor_laravel_prompts_src_concerns_truncation_php", "target": "invalidargumentexception", "relation": "imports", "confidence": "EXTRACTED", "source_file": "D:\\Projects\\ev-charging-mvp\\backend\\vendor\\laravel\\prompts\\src\\Concerns\\Truncation.php", "source_location": "L5", "weight": 1.0}, {"source": "d_projects_ev_charging_mvp_backend_vendor_laravel_prompts_src_concerns_truncation_php", "target": "concerns_truncation_truncate", "relation": "contains", "confidence": "EXTRACTED", "source_file": "D:\\Projects\\ev-charging-mvp\\backend\\vendor\\laravel\\prompts\\src\\Concerns\\Truncation.php", "source_location": "L12", "weight": 1.0}], "raw_calls": [{"caller_nid": "concerns_truncation_truncate", "callee": "mb_strwidth", "source_file": "D:\\Projects\\ev-charging-mvp\\backend\\vendor\\laravel\\prompts\\src\\Concerns\\Truncation.php", "source_location": "L18"}, {"caller_nid": "concerns_truncation_truncate", "callee": "mb_strimwidth", "source_file": "D:\\Projects\\ev-charging-mvp\\backend\\vendor\\laravel\\prompts\\src\\Concerns\\Truncation.php", "source_location": "L18"}]}