{"nodes": [{"id": "d_projects_ev_charging_mvp_backend_vendor_stripe_stripe_php_lib_issuing_transaction_php", "label": "Transaction.php", "file_type": "code", "source_file": "D:\\Projects\\ev-charging-mvp\\backend\\vendor\\stripe\\stripe-php\\lib\\Issuing\\Transaction.php", "source_location": "L1"}, {"id": "issuing_transaction_transaction", "label": "Transaction", "file_type": "code", "source_file": "D:\\Projects\\ev-charging-mvp\\backend\\vendor\\stripe\\stripe-php\\lib\\Issuing\\Transaction.php", "source_location": "L37"}, {"id": "issuing_transaction_transaction_all", "label": ".all()", "file_type": "code", "source_file": "D:\\Projects\\ev-charging-mvp\\backend\\vendor\\stripe\\stripe-php\\lib\\Issuing\\Transaction.php", "source_location": "L62"}, {"id": "issuing_transaction_transaction_retrieve", "label": ".retrieve()", "file_type": "code", "source_file": "D:\\Projects\\ev-charging-mvp\\backend\\vendor\\stripe\\stripe-php\\lib\\Issuing\\Transaction.php", "source_location": "L79"}, {"id": "issuing_transaction_transaction_update", "label": ".update()", "file_type": "code", "source_file": "D:\\Projects\\ev-charging-mvp\\backend\\vendor\\stripe\\stripe-php\\lib\\Issuing\\Transaction.php", "source_location": "L101"}], "edges": [{"source": "d_projects_ev_charging_mvp_backend_vendor_stripe_stripe_php_lib_issuing_transaction_php", "target": "issuing_transaction_transaction", "relation": "contains", "confidence": "EXTRACTED", "source_file": "D:\\Projects\\ev-charging-mvp\\backend\\vendor\\stripe\\stripe-php\\lib\\Issuing\\Transaction.php", "source_location": "L37", "weight": 1.0}, {"source": "issuing_transaction_transaction", "target": "issuing_transaction_transaction_all", "relation": "method", "confidence": "EXTRACTED", "source_file": "D:\\Projects\\ev-charging-mvp\\backend\\vendor\\stripe\\stripe-php\\lib\\Issuing\\Transaction.php", "source_location": "L62", "weight": 1.0}, {"source": "issuing_transaction_transaction", "target": "issuing_transaction_transaction_retrieve", "relation": "method", "confidence": "EXTRACTED", "source_file": "D:\\Projects\\ev-charging-mvp\\backend\\vendor\\stripe\\stripe-php\\lib\\Issuing\\Transaction.php", "source_location": "L79", "weight": 1.0}, {"source": "issuing_transaction_transaction", "target": "issuing_transaction_transaction_update", "relation": "method", "confidence": "EXTRACTED", "source_file": "D:\\Projects\\ev-charging-mvp\\backend\\vendor\\stripe\\stripe-php\\lib\\Issuing\\Transaction.php", "source_location": "L101", "weight": 1.0}], "raw_calls": [{"caller_nid": "issuing_transaction_transaction_all", "callee": "static", "source_file": "D:\\Projects\\ev-charging-mvp\\backend\\vendor\\stripe\\stripe-php\\lib\\Issuing\\Transaction.php", "source_location": "L64"}, {"caller_nid": "issuing_transaction_transaction_all", "callee": "static", "source_file": "D:\\Projects\\ev-charging-mvp\\backend\\vendor\\stripe\\stripe-php\\lib\\Issuing\\Transaction.php", "source_location": "L66"}, {"caller_nid": "issuing_transaction_transaction_retrieve", "callee": "\\Stripe\\Util\\RequestOptions", "source_file": "D:\\Projects\\ev-charging-mvp\\backend\\vendor\\stripe\\stripe-php\\lib\\Issuing\\Transaction.php", "source_location": "L81"}, {"caller_nid": "issuing_transaction_transaction_retrieve", "callee": "refresh", "source_file": "D:\\Projects\\ev-charging-mvp\\backend\\vendor\\stripe\\stripe-php\\lib\\Issuing\\Transaction.php", "source_location": "L83"}, {"caller_nid": "issuing_transaction_transaction_update", "callee": "self", "source_file": "D:\\Projects\\ev-charging-mvp\\backend\\vendor\\stripe\\stripe-php\\lib\\Issuing\\Transaction.php", "source_location": "L103"}, {"caller_nid": "issuing_transaction_transaction_update", "callee": "static", "source_file": "D:\\Projects\\ev-charging-mvp\\backend\\vendor\\stripe\\stripe-php\\lib\\Issuing\\Transaction.php", "source_location": "L104"}, {"caller_nid": "issuing_transaction_transaction_update", "callee": "static", "source_file": "D:\\Projects\\ev-charging-mvp\\backend\\vendor\\stripe\\stripe-php\\lib\\Issuing\\Transaction.php", "source_location": "L106"}, {"caller_nid": "issuing_transaction_transaction_update", "callee": "\\Stripe\\Util\\Util", "source_file": "D:\\Projects\\ev-charging-mvp\\backend\\vendor\\stripe\\stripe-php\\lib\\Issuing\\Transaction.php", "source_location": "L107"}, {"caller_nid": "issuing_transaction_transaction_update", "callee": "setLastResponse", "source_file": "D:\\Projects\\ev-charging-mvp\\backend\\vendor\\stripe\\stripe-php\\lib\\Issuing\\Transaction.php", "source_location": "L108"}]}