{"nodes": [{"id": "d_projects_ev_charging_mvp_backoffice_src_ts_tailwind_components_dock_dock_tsx", "label": "Dock.tsx", "file_type": "code", "source_file": "D:\\Projects\\ev-charging-mvp\\backoffice\\src\\ts-tailwind\\Components\\Dock\\Dock.tsx", "source_location": "L1"}], "edges": [{"source": "d_projects_ev_charging_mvp_backoffice_src_ts_tailwind_components_dock_dock_tsx", "target": "react", "relation": "imports_from", "confidence": "EXTRACTED", "source_file": "D:\\Projects\\ev-charging-mvp\\backoffice\\src\\ts-tailwind\\Components\\Dock\\Dock.tsx", "source_location": "L3", "weight": 1.0}, {"source": "d_projects_ev_charging_mvp_backoffice_src_ts_tailwind_components_dock_dock_tsx", "target": "react", "relation": "imports_from", "confidence": "EXTRACTED", "source_file": "D:\\Projects\\ev-charging-mvp\\backoffice\\src\\ts-tailwind\\Components\\Dock\\Dock.tsx", "source_location": "L12", "weight": 1.0}], "raw_calls": []}